vetsa/__init__.py
vetsa/client.py
vetsa-0.1.0.dist-info/METADATA
vetsa-0.1.0.dist-info/WHEEL
vetsa-0.1.0.dist-info/entry_points.txt
vetsa-0.1.0.dist-info/top_level.txt
vetsa-0.1.0.dist-info/RECORD
