Metadata-Version: 2.4
Name: vetsa
Version: 0.1.0
Summary: Cliente oficial de Python para Vetsa Intelligence API
Author-email: Daniel Luna <ceo@vetsa.site>
License: MIT
Project-URL: Homepage, https://api.vetsa.site
Project-URL: Source, https://github.com/mainvortexdev/vetsa-python
Keywords: vetsa,ai,intelligence,voice,api
Requires-Python: >=3.8
Requires-Dist: requests>=2.28.0
Requires-Dist: websockets>=11.0
Requires-Dist: pyaudio>=0.2.13
